zcli/__init__.py
zcli/acctab.py
zcli/clargs.py
zcli/commands.py
zcli/main.py
zcli/operations.py
zcli/saferjson.py
zcli/ui.py
zcli/zcashcli.py
zcli/tests/__init__.py
zcli/tests/test_clargs.py
zcli/tests/test_commands.py
zcli/tests/test_main.py
zcli/tests/test_operations.py
zcli/tests/test_saferjson.py
zcli/tests/test_ui.py
zcli/tests/test_zcli.py
zcli/tests/utils.py
zcli-0.1.3.dist-info/METADATA
zcli-0.1.3.dist-info/WHEEL
zcli-0.1.3.dist-info/entry_points.txt
zcli-0.1.3.dist-info/top_level.txt
zcli-0.1.3.dist-info/RECORD
