Metadata-Version: 2.1
Name: zcli
Version: 0.1.3
Summary: ('Simply certain useful tasks on top of the Zcash RPC interface.',)
Home-page: https://github.com/nejucomo/zcli
Author: Nathan Wilcox
Author-email: nejucomo+dev@gmail.com
License: GPLv3
Platform: UNKNOWN
Requires-Dist: functable (>=0.2)
Requires-Dist: genty (>=1.3.2)
Requires-Dist: pathlib2 (>=2.3.0)
Requires-Dist: mock (>=2.0.0)
